hippos/PARAMETERS.py
hippos/SIMILARITY_FORMULA.py
hippos/__init__.py
hippos/_version.py
hippos/hippos.py
hippos/hippos_genref.py
hippos/ifp_processing.py
hippos/similarity.py
hippos/initialize/__init__.py
hippos/initialize/parse_conf.py
hippos/initialize/parse_docking_conf.py
hippos/tests/__init__.py
hippos/tests/test_hippos.py
hippos/tests/test_parse_config.py
hippos/tests/test_parse_docking_conf.py
hippos/tests/test_similarity_formula.py
pyplif_hippos/PARAMETERS.py
pyplif_hippos/SIMILARITY_FORMULA.py
pyplif_hippos/__init__.py
pyplif_hippos/_version.py
pyplif_hippos/hippos.py
pyplif_hippos/hippos_genref.py
pyplif_hippos/ifp_processing.py
pyplif_hippos/similarity.py
pyplif_hippos/data/README.md
pyplif_hippos/data/look_and_say.dat
pyplif_hippos/initialize/__init__.py
pyplif_hippos/initialize/parse_conf.py
pyplif_hippos/initialize/parse_docking_conf.py
pyplif_hippos/tests/__init__.py
pyplif_hippos/tests/test_hippos.py
pyplif_hippos/tests/test_parse_config.py
pyplif_hippos/tests/test_parse_docking_conf.py
pyplif_hippos/tests/test_similarity_formula.py
pyplif_hippos/tests/data/README.md
pyplif_hippos/tests/data/plants/1b9s-protein.mol2
pyplif_hippos/tests/data/plants/247120.mol2
pyplif_hippos/tests/data/plants/plants-001.conf
pyplif_hippos/tests/data/plants/plants_001/bestranking.csv
pyplif_hippos/tests/data/plants/plants_001/constraints.csv
pyplif_hippos/tests/data/plants/plants_001/correspondingNames.csv
pyplif_hippos/tests/data/plants/plants_001/descent_247120_1.dat
pyplif_hippos/tests/data/plants/plants_001/docked_ligands.mol2
pyplif_hippos/tests/data/plants/plants_001/docked_proteins.mol2
pyplif_hippos/tests/data/plants/plants_001/features.csv
pyplif_hippos/tests/data/plants/plants_001/ligand.log
pyplif_hippos/tests/data/plants/plants_001/optimizer.csv
pyplif_hippos/tests/data/plants/plants_001/optimizer.log
pyplif_hippos/tests/data/plants/plants_001/plantsconfig
pyplif_hippos/tests/data/plants/plants_001/protein.log
pyplif_hippos-0.1.0.dist-info/LICENSE.txt
pyplif_hippos-0.1.0.dist-info/METADATA
pyplif_hippos-0.1.0.dist-info/WHEEL
pyplif_hippos-0.1.0.dist-info/entry_points.txt
pyplif_hippos-0.1.0.dist-info/top_level.txt
pyplif_hippos-0.1.0.dist-info/RECORD
