Metadata-Version: 2.1
Name: pyplif-hippos
Version: 0.1.0
Summary: UNKNOWN
Home-page: https://github.com/radifar/PyPLIF-HIPPOS
Author: Muhammad Radifar
Author-email: muhammad.radifar@picomps.org
License: MHPND
Platform: UNKNOWN
Requires-Dist: openbabel (>=2.4.0)
Requires-Dist: numpy (>=1.6.2)
Requires-Dist: bitstring (>=0.8.1)
